jupyter_run/__init__.py
jupyter_run/_version.py
jupyter_run/handlers.py
jupyter_run/tests/__init__.py
jupyter_run/tests/test_handlers.py
jupyter_run-0.0.3.data/data/etc/jupyter/jupyter_notebook_config.d/jupyter_run.json
jupyter_run-0.0.3.data/data/etc/jupyter/jupyter_server_config.d/jupyter_run.json
jupyter_run-0.0.3.data/data/share/jupyter/labextensions/@datalayer/jupyter-run/build_log.json
jupyter_run-0.0.3.data/data/share/jupyter/labextensions/@datalayer/jupyter-run/package.json
jupyter_run-0.0.3.data/data/share/jupyter/labextensions/@datalayer/jupyter-run/schemas/@datalayer/jupyter-run/package.json.orig
jupyter_run-0.0.3.data/data/share/jupyter/labextensions/@datalayer/jupyter-run/schemas/@datalayer/jupyter-run/plugin.json
jupyter_run-0.0.3.data/data/share/jupyter/labextensions/@datalayer/jupyter-run/static/design_icons_lib_index_js.18fca5daf1f9a00c7670.js
jupyter_run-0.0.3.data/data/share/jupyter/labextensions/@datalayer/jupyter-run/static/design_icons_lib_index_js.18fca5daf1f9a00c7670.js.map
jupyter_run-0.0.3.data/data/share/jupyter/labextensions/@datalayer/jupyter-run/static/lib_index_js.4a939d660c89f590450e.js
jupyter_run-0.0.3.data/data/share/jupyter/labextensions/@datalayer/jupyter-run/static/lib_index_js.4a939d660c89f590450e.js.map
jupyter_run-0.0.3.data/data/share/jupyter/labextensions/@datalayer/jupyter-run/static/node_modules_object-assign_index_js.d9f7d9f7f89acb842935.js
jupyter_run-0.0.3.data/data/share/jupyter/labextensions/@datalayer/jupyter-run/static/node_modules_object-assign_index_js.d9f7d9f7f89acb842935.js.map
jupyter_run-0.0.3.data/data/share/jupyter/labextensions/@datalayer/jupyter-run/static/remoteEntry.4233b9d5cdfb3e6225c7.js
jupyter_run-0.0.3.data/data/share/jupyter/labextensions/@datalayer/jupyter-run/static/remoteEntry.4233b9d5cdfb3e6225c7.js.map
jupyter_run-0.0.3.data/data/share/jupyter/labextensions/@datalayer/jupyter-run/static/style.js
jupyter_run-0.0.3.dist-info/METADATA
jupyter_run-0.0.3.dist-info/WHEEL
jupyter_run-0.0.3.dist-info/licenses/LICENSE
jupyter_run-0.0.3.dist-info/RECORD
